mcwb/__init__.py
mcwb/_version_git.py
mcwb/api.py
mcwb/blocks.py
mcwb/functions.py
mcwb/itemlists.py
mcwb/polygon.py
mcwb/types.py
mcwb/volume.py
mcwb-0.3.0.dist-info/licenses/LICENSE.txt
mcwb-0.3.0.dist-info/METADATA
mcwb-0.3.0.dist-info/WHEEL
mcwb-0.3.0.dist-info/top_level.txt
mcwb-0.3.0.dist-info/RECORD
