Metadata-Version: 2.4
Name: mcwb
Version: 0.3.0
Summary: A Minecraft world builder library.
Home-page: https://github.com/conqp/mcwb
Author: Richard Neumann
Author-email: mail@richard-neumann.de
License: GPLv3
Keywords: minecraft world builder python rcon
Classifier: Development Status :: 4 - Beta
Classifier: Programming Language :: Python :: 3.13
License-File: LICENSE.txt
Requires-Dist: numpy
Requires-Dist: mcipc
Requires-Dist: rcon
Provides-Extra: dev
Requires-Dist: black; extra == "dev"
Requires-Dist: isort; extra == "dev"
Requires-Dist: pytest-cov; extra == "dev"
Requires-Dist: pytest-mypy; extra == "dev"
Requires-Dist: flake8; extra == "dev"
Requires-Dist: pytest-flake8; extra == "dev"
Requires-Dist: pytest-black; extra == "dev"
Requires-Dist: flake8-isort; extra == "dev"
Requires-Dist: sphinx-rtd-theme-github-versions; extra == "dev"
Requires-Dist: importlib-metadata; extra == "dev"
Requires-Dist: docker; extra == "dev"
Provides-Extra: include-package-data
Requires-Dist: False; extra == "include-package-data"
Dynamic: license-file
